README.md
setup.cfg
setup.py
decimalcontext/__init__.py
decimalcontext.egg-info/PKG-INFO
decimalcontext.egg-info/SOURCES.txt
decimalcontext.egg-info/dependency_links.txt
decimalcontext.egg-info/requires.txt
decimalcontext.egg-info/top_level.txt